bavard_ml_utils/__init__.py
bavard_ml_utils/aws/__init__.py
bavard_ml_utils/aws/s3.py
bavard_ml_utils/gcp/__init__.py
bavard_ml_utils/gcp/gcs.py
bavard_ml_utils/gcp/logging.py
bavard_ml_utils/gcp/pub_sub.py
bavard_ml_utils/ml/__init__.py
bavard_ml_utils/ml/conv_graph.py
bavard_ml_utils/ml/dataset.py
bavard_ml_utils/ml/utils.py
bavard_ml_utils/persistence/__init__.py
bavard_ml_utils/persistence/artifact_manager.py
bavard_ml_utils/persistence/record_store/__init__.py
bavard_ml_utils/persistence/record_store/base.py
bavard_ml_utils/persistence/record_store/dynamodb.py
bavard_ml_utils/persistence/record_store/firestore.py
bavard_ml_utils/persistence/record_store/memory.py
bavard_ml_utils/persistence/serialization.py
bavard_ml_utils/types/__init__.py
bavard_ml_utils/types/agent.py
bavard_ml_utils/types/conversations/__init__.py
bavard_ml_utils/types/conversations/actions.py
bavard_ml_utils/types/conversations/conversation.py
bavard_ml_utils/types/conversations/dialogue_turns.py
bavard_ml_utils/types/data.py
bavard_ml_utils/types/ml.py
bavard_ml_utils/types/nlu.py
bavard_ml_utils/types/utils.py
bavard_ml_utils/utils.py
bavard_ml_utils/web/__init__.py
bavard_ml_utils/web/errors.py
bavard_ml_utils/web/web_service.py
bavard_ml_utils-0.2.10.dist-info/LICENSE
bavard_ml_utils-0.2.10.dist-info/WHEEL
bavard_ml_utils-0.2.10.dist-info/METADATA
bavard_ml_utils-0.2.10.dist-info/RECORD
