Metadata-Version: 2.1
Name: bavard-ml-utils
Version: 0.2.10
Summary: Utilities for machine learning, python web services, and cloud infrastructure
Home-page: https://github.com/bavard-ai/bavard-ml-utils
License: MIT
Author: Bavard AI, Inc.
Author-email: dev@bavard.ai
Requires-Python: >=3.8,<4.0
Classifier: License :: OSI Approved :: MIT License
Classifier: Programming Language :: Python :: 3
Classifier: Programming Language :: Python :: 3.10
Classifier: Programming Language :: Python :: 3.8
Classifier: Programming Language :: Python :: 3.9
Provides-Extra: aws
Provides-Extra: gcp
Provides-Extra: ml
Requires-Dist: boto3 (>=1.20.16,<2.0.0); extra == "aws"
Requires-Dist: fastapi (>=0.63.0,<1.0.0)
Requires-Dist: google-cloud-error-reporting (>=1.1.1,<2.0.0); extra == "gcp"
Requires-Dist: google-cloud-firestore (>=2.3.2,<3.0.0); extra == "gcp"
Requires-Dist: google-cloud-pubsub (>=2.2.0,<3.0.0); extra == "gcp"
Requires-Dist: google-cloud-storage (>=1.35.1,<2.0.0); extra == "gcp"
Requires-Dist: loguru (>=0.5.1,<1.0.0)
Requires-Dist: networkx (>=2.6.3,<3.0.0); extra == "ml"
Requires-Dist: numpy (>=1.19.2,<2.0.0); extra == "ml"
Requires-Dist: pydantic (>=1.7.3,<2.0.0)
Requires-Dist: requests (>=2.21.0,<3.0.0)
Requires-Dist: scikit-learn (>=0.24.2,<2.0.0); extra == "ml"
Project-URL: Documentation, https://docs-bavard-ml-utils.web.app/
Project-URL: Repository, https://github.com/bavard-ai/bavard-ml-utils
